textual_pyfiglet/__init__.py
textual_pyfiglet/figletwidget.py
textual_pyfiglet/fonts_list.py
textual_pyfiglet/help.md
textual_pyfiglet/py.typed
textual_pyfiglet/demo/__init__.py
textual_pyfiglet/demo/datawidget.py
textual_pyfiglet/demo/main.py
textual_pyfiglet/demo/screens.py
textual_pyfiglet/demo/settingsbar.py
textual_pyfiglet/demo/styles.tcss
textual_pyfiglet/demo/validators.py
textual_pyfiglet-1.1.0.dist-info/METADATA
textual_pyfiglet-1.1.0.dist-info/WHEEL
textual_pyfiglet-1.1.0.dist-info/entry_points.txt
textual_pyfiglet-1.1.0.dist-info/licenses/LICENSE
textual_pyfiglet-1.1.0.dist-info/RECORD
