Metadata-Version: 2.4
Name: textual-pyfiglet
Version: 1.1.0
Summary: A Widget implementation of PyFiglet for Textual
Project-URL: Repository, https://github.com/edward-jazzhands/textual-pyfiglet
Project-URL: Documentation, https://edward-jazzhands.github.io/libraries/textual-pyfiglet/
Project-URL: Changelog, https://github.com/edward-jazzhands/textual-pyfiglet/blob/master/CHANGELOG.md
Author-email: edward-jazzhands <ed.jazzhands@gmail.com>
License: MIT
License-File: LICENSE
Keywords: ascii,ascii-art,figlet,pyfiglet,python,textual,tui,widget
Classifier: Development Status :: 5 - Production/Stable
Classifier: License :: OSI Approved :: MIT License
Classifier: Operating System :: OS Independent
Classifier: Programming Language :: Python
Classifier: Programming Language :: Python :: 3 :: Only
Classifier: Programming Language :: Python :: 3.9
Classifier: Programming Language :: Python :: 3.10
Classifier: Programming Language :: Python :: 3.11
Classifier: Programming Language :: Python :: 3.12
Classifier: Programming Language :: Python :: 3.13
Requires-Python: >=3.9
Requires-Dist: pyfiglet>=1.0.3
Requires-Dist: textual-coloromatic>=1.0.0
Requires-Dist: textual-slidecontainer>=1.0.0
Requires-Dist: textual<6.0.0,>=3.0.0
